categories_api/__init__.py
categories_api/urls.py
categories_api/viewsets.py
categories_api/api/__init__.py
categories_api/api/urls.py
categories_api/api/viewsets.py
categories_api/api/tests/__init__.py
categories_api/api/tests/test_api.py
categories_api/tests/__init__.py
categories_api/tests/test_api.py
django_categories_api-0.2.2.dist-info/LICENSE.txt
django_categories_api-0.2.2.dist-info/METADATA
django_categories_api-0.2.2.dist-info/NOTICES.txt
django_categories_api-0.2.2.dist-info/WHEEL
django_categories_api-0.2.2.dist-info/top_level.txt
django_categories_api-0.2.2.dist-info/RECORD
