Metadata-Version: 2.1
Name: django-categories-api
Version: 0.2.2
Summary: Django-rest-framework API for django-categories
Home-page: http://github.com/petrdlouhy/django-categories-api
Author: Petr Dlouhý
Author-email: petr.dlouhy@email.cz
Classifier: Framework :: Django
License-File: LICENSE.txt
License-File: NOTICES.txt
Requires-Dist: django-categories
